db_model_generator/__init__.py
db_model_generator/constants.py
db_model_generator/core.py
db_model_generator/generator.py
db_model_generator/typings.py
db_model_generator/warnings.py
db_model_generator-1.5.1.dist-info/licenses/LICENSE
db_model_generator-1.5.1.dist-info/METADATA
db_model_generator-1.5.1.dist-info/WHEEL
db_model_generator-1.5.1.dist-info/entry_points.txt
db_model_generator-1.5.1.dist-info/top_level.txt
db_model_generator-1.5.1.dist-info/RECORD
