Metadata-Version: 2.4
Name: db-model-generator
Version: 1.5.1
Summary: Генератор моделей sqlalchemy из таблиц базы данных
Home-page: https://github.com/MagIlyasDOMA/db_model_generator
Author: Маг Ильяс DOMA (MagIlyasDOMA)
Author-email: magilyas.doma.09@list.ru
License: MIT
Project-URL: Homepage, https://github.com/MagIlyasDOMA/db_model_generator
Project-URL: Documentation, https://magilyasdoma.github.io/db_model_generator
Project-URL: Repository, https://github.com/MagIlyasDOMA/db_model_generator
Project-URL: Issues, https://github.com/MagIlyasDOMA/db_model_generator/issues
Keywords: sqlalchemy,wtforms,code-generation,database,models,forms
Classifier: Development Status :: 5 - Production/Stable
Classifier: Intended Audience :: Developers
Classifier: License :: OSI Approved :: MIT License
Classifier: Programming Language :: Python :: 3
Classifier: Programming Language :: Python :: 3.10
Classifier: Programming Language :: Python :: 3.11
Classifier: Programming Language :: Python :: 3.12
Classifier: Programming Language :: Python :: 3.13
Classifier: Programming Language :: Python :: 3.14
Classifier: Framework :: Flask
Classifier: Operating System :: Microsoft :: Windows
Classifier: Operating System :: Microsoft :: Windows :: Windows 10
Classifier: Operating System :: Microsoft :: Windows :: Windows 11
Classifier: Topic :: Database
Classifier: Topic :: Database :: Database Engines/Servers
Classifier: Topic :: Scientific/Engineering :: Information Analysis
Classifier: Topic :: Software Development :: Libraries :: Python Modules
Requires-Python: >=3.10
License-File: LICENSE
Requires-Dist: sqlalchemy==2.0.44
Requires-Dist: deep-translator>=1.11.4
Requires-Dist: tab4>=0.1.0
Requires-Dist: python-dotenv>=1.0.0
Requires-Dist: undefined-python>=1.0.0
Requires-Dist: typing-extensions>=4.0.0; python_version < "3.8"
Requires-Dist: requests>=2.0.0
Provides-Extra: base
Requires-Dist: sqlalchemy==2.0.44; extra == "base"
Requires-Dist: deep-translator>=1.11.4; extra == "base"
Requires-Dist: tab4>=0.1.0; extra == "base"
Requires-Dist: python-dotenv>=1.0.0; extra == "base"
Requires-Dist: undefined-python>=1.1.0; extra == "base"
Requires-Dist: typing-extensions>=4.0.0; python_version < "3.8" and extra == "base"
Requires-Dist: requests>=2.0.0; extra == "base"
Provides-Extra: flask
Requires-Dist: sqlalchemy==2.0.44; extra == "flask"
Requires-Dist: deep-translator>=1.11.4; extra == "flask"
Requires-Dist: tab4>=0.1.0; extra == "flask"
Requires-Dist: python-dotenv>=1.0.0; extra == "flask"
Requires-Dist: undefined-python>=1.1.0; extra == "flask"
Requires-Dist: typing-extensions>=4.0.0; python_version < "3.8" and extra == "flask"
Requires-Dist: requests>=2.0.0; extra == "flask"
Requires-Dist: flask<4.0.0,>=3.1.1; extra == "flask"
Requires-Dist: flask-sqlalchemy==3.1.1; extra == "flask"
Requires-Dist: flask-wtf==1.2.2; extra == "flask"
Requires-Dist: wtforms==3.2.1; extra == "flask"
Provides-Extra: all
Requires-Dist: sqlalchemy==2.0.44; extra == "all"
Requires-Dist: deep-translator>=1.11.4; extra == "all"
Requires-Dist: tab4>=0.1.0; extra == "all"
Requires-Dist: python-dotenv>=1.0.0; extra == "all"
Requires-Dist: undefined-python>=1.1.0; extra == "all"
Requires-Dist: typing-extensions>=4.0.0; python_version < "3.8" and extra == "all"
Requires-Dist: requests>=2.0.0; extra == "all"
Requires-Dist: flask<4.0.0,>=3.1.1; extra == "all"
Requires-Dist: flask-sqlalchemy==3.1.1; extra == "all"
Requires-Dist: flask-wtf==1.2.2; extra == "all"
Requires-Dist: wtforms==3.2.1; extra == "all"
Dynamic: author
Dynamic: author-email
Dynamic: classifier
Dynamic: description
Dynamic: description-content-type
Dynamic: home-page
Dynamic: keywords
Dynamic: license
Dynamic: license-file
Dynamic: project-url
Dynamic: provides-extra
Dynamic: requires-dist
Dynamic: requires-python
Dynamic: summary
